firstname_to_nationality/__init__.py
firstname_to_nationality/best-model.pt
firstname_to_nationality/city_to_nationality.py
firstname_to_nationality/country_nationality.csv
firstname_to_nationality/firstname_nationalities.pkl
firstname_to_nationality/firstname_to_country.py
firstname_to_nationality/firstname_to_nationality.py
firstname_to_nationality-1.1.14.dist-info/licenses/LICENSE
firstname_to_nationality-1.1.14.dist-info/METADATA
firstname_to_nationality-1.1.14.dist-info/WHEEL
firstname_to_nationality-1.1.14.dist-info/top_level.txt
firstname_to_nationality-1.1.14.dist-info/RECORD
