Metadata-Version: 2.4
Name: firstname-to-nationality
Version: 1.1.14
Summary: Nationality Prediction from Firstname using Python 3.13 and scikit-learn
Home-page: https://github.com/callidio/firstname_to_nationality
Author: Firstname to Nationality Team
Author-email: 
License: MIT
Project-URL: Documentation, https://github.com/callidio/firstname_to_nationality#readme
Project-URL: Source, https://github.com/callidio/firstname_to_nationality
Project-URL: Tracker, https://github.com/callidio/firstname_to_nationality/issues
Keywords: firstname nationality prediction names machine-learning nlp
Classifier: Development Status :: 4 - Beta
Classifier: Intended Audience :: Developers
Classifier: Intended Audience :: Science/Research
Classifier: License :: OSI Approved :: MIT License
Classifier: Operating System :: OS Independent
Classifier: Programming Language :: Python :: 3
Classifier: Programming Language :: Python :: 3.13
Classifier: Topic :: Scientific/Engineering :: Artificial Intelligence
Classifier: Topic :: Text Processing :: Linguistic
Classifier: Typing :: Typed
Requires-Python: >=3.11
License-File: LICENSE
Requires-Dist: numpy==2.4.1
Requires-Dist: scikit-learn==1.8.0
Requires-Dist: joblib==1.5.3
Requires-Dist: pandas==3.0.0
Requires-Dist: geopy==2.4.1
Provides-Extra: viz
Requires-Dist: matplotlib==3.10.8; extra == "viz"
Requires-Dist: seaborn==0.13.2; extra == "viz"
Provides-Extra: dev
Requires-Dist: pytest==9.0.2; extra == "dev"
Requires-Dist: pytest-cov==7.0.0; extra == "dev"
Requires-Dist: black==26.1.0; extra == "dev"
Requires-Dist: flake8==7.3.0; extra == "dev"
Requires-Dist: isort==7.0.0; extra == "dev"
Requires-Dist: pylint==4.0.4; extra == "dev"
Requires-Dist: mypy==1.19.1; extra == "dev"
Requires-Dist: types-requests==2.32.4.20260107; extra == "dev"
Requires-Dist: twine==6.2.0; extra == "dev"
Requires-Dist: build==1.4.0; extra == "dev"
Dynamic: author
Dynamic: classifier
Dynamic: description
Dynamic: description-content-type
Dynamic: home-page
Dynamic: keywords
Dynamic: license
Dynamic: license-file
Dynamic: project-url
Dynamic: provides-extra
Dynamic: requires-dist
Dynamic: requires-python
Dynamic: summary
